smart/__init__.py
smart/replacess_pycahr.py
pycahrm_external-1.1.2.dist-info/METADATA
pycahrm_external-1.1.2.dist-info/WHEEL
pycahrm_external-1.1.2.dist-info/top_level.txt
pycahrm_external-1.1.2.dist-info/RECORD
